<?xml version="1.0" encoding="UTF-8"?>
<?xml-stylesheet href="CoreNLP-to-HTML.xsl" type="text/xsl"?>
<root>
  <document>
    <sentences>
      <sentence id="1">
        <tokens>
          <token id="1">
            <word>[</word>
            <lemma>[</lemma>
            <CharacterOffsetBegin>0</CharacterOffsetBegin>
            <CharacterOffsetEnd>1</CharacterOffsetEnd>
            <POS>-LRB-</POS>
          </token>
          <token id="2">
            <word>XSUM</word>
            <lemma>XSUM</lemma>
            <CharacterOffsetBegin>1</CharacterOffsetBegin>
            <CharacterOffsetEnd>5</CharacterOffsetEnd>
            <POS>NNP</POS>
          </token>
          <token id="3">
            <word>]</word>
            <lemma>]</lemma>
            <CharacterOffsetBegin>5</CharacterOffsetBegin>
            <CharacterOffsetEnd>6</CharacterOffsetEnd>
            <POS>-RRB-</POS>
          </token>
          <token id="4">
            <word>URL</word>
            <lemma>URL</lemma>
            <CharacterOffsetBegin>6</CharacterOffsetBegin>
            <CharacterOffsetEnd>9</CharacterOffsetEnd>
            <POS>NNP</POS>
          </token>
          <token id="5">
            <word>[</word>
            <lemma>[</lemma>
            <CharacterOffsetBegin>9</CharacterOffsetBegin>
            <CharacterOffsetEnd>10</CharacterOffsetEnd>
            <POS>-LRB-</POS>
          </token>
          <token id="6">
            <word>XSUM</word>
            <lemma>XSUM</lemma>
            <CharacterOffsetBegin>10</CharacterOffsetBegin>
            <CharacterOffsetEnd>14</CharacterOffsetEnd>
            <POS>NNP</POS>
          </token>
          <token id="7">
            <word>]</word>
            <lemma>]</lemma>
            <CharacterOffsetBegin>14</CharacterOffsetBegin>
            <CharacterOffsetEnd>15</CharacterOffsetEnd>
            <POS>-RRB-</POS>
          </token>
          <token id="8">
            <word>http://web.archive.org/web/20170811075951/http://www.bbc.co.uk/news/uk-england-humber-40879184</word>
            <lemma>http://web.archive.org/web/20170811075951/http://www.bbc.co.uk/news/uk-england-humber-40879184</lemma>
            <CharacterOffsetBegin>16</CharacterOffsetBegin>
            <CharacterOffsetEnd>110</CharacterOffsetEnd>
            <POS>ADD</POS>
          </token>
          <token id="9">
            <word>[</word>
            <lemma>[</lemma>
            <CharacterOffsetBegin>112</CharacterOffsetBegin>
            <CharacterOffsetEnd>113</CharacterOffsetEnd>
            <POS>-LRB-</POS>
          </token>
          <token id="10">
            <word>XSUM</word>
            <lemma>XSUM</lemma>
            <CharacterOffsetBegin>113</CharacterOffsetBegin>
            <CharacterOffsetEnd>117</CharacterOffsetEnd>
            <POS>NNP</POS>
          </token>
          <token id="11">
            <word>]</word>
            <lemma>]</lemma>
            <CharacterOffsetBegin>117</CharacterOffsetBegin>
            <CharacterOffsetEnd>118</CharacterOffsetEnd>
            <POS>-RRB-</POS>
          </token>
          <token id="12">
            <word>INTRODUCTION</word>
            <lemma>introduction</lemma>
            <CharacterOffsetBegin>118</CharacterOffsetBegin>
            <CharacterOffsetEnd>130</CharacterOffsetEnd>
            <POS>NN</POS>
          </token>
          <token id="13">
            <word>[</word>
            <lemma>[</lemma>
            <CharacterOffsetBegin>130</CharacterOffsetBegin>
            <CharacterOffsetEnd>131</CharacterOffsetEnd>
            <POS>-LRB-</POS>
          </token>
          <token id="14">
            <word>XSUM</word>
            <lemma>XSUM</lemma>
            <CharacterOffsetBegin>131</CharacterOffsetBegin>
            <CharacterOffsetEnd>135</CharacterOffsetEnd>
            <POS>NNP</POS>
          </token>
          <token id="15">
            <word>]</word>
            <lemma>]</lemma>
            <CharacterOffsetBegin>135</CharacterOffsetBegin>
            <CharacterOffsetEnd>136</CharacterOffsetEnd>
            <POS>-RRB-</POS>
          </token>
          <token id="16">
            <word>A</word>
            <lemma>a</lemma>
            <CharacterOffsetBegin>137</CharacterOffsetBegin>
            <CharacterOffsetEnd>138</CharacterOffsetEnd>
            <POS>DT</POS>
          </token>
          <token id="17">
            <word>woman</word>
            <lemma>woman</lemma>
            <CharacterOffsetBegin>139</CharacterOffsetBegin>
            <CharacterOffsetEnd>144</CharacterOffsetEnd>
            <POS>NN</POS>
          </token>
          <token id="18">
            <word>has</word>
            <lemma>have</lemma>
            <CharacterOffsetBegin>145</CharacterOffsetBegin>
            <CharacterOffsetEnd>148</CharacterOffsetEnd>
            <POS>VBZ</POS>
          </token>
          <token id="19">
            <word>been</word>
            <lemma>be</lemma>
            <CharacterOffsetBegin>149</CharacterOffsetBegin>
            <CharacterOffsetEnd>153</CharacterOffsetEnd>
            <POS>VBN</POS>
          </token>
          <token id="20">
            <word>charged</word>
            <lemma>charge</lemma>
            <CharacterOffsetBegin>154</CharacterOffsetBegin>
            <CharacterOffsetEnd>161</CharacterOffsetEnd>
            <POS>VBN</POS>
          </token>
          <token id="21">
            <word>with</word>
            <lemma>with</lemma>
            <CharacterOffsetBegin>162</CharacterOffsetBegin>
            <CharacterOffsetEnd>166</CharacterOffsetEnd>
            <POS>IN</POS>
          </token>
          <token id="22">
            <word>murder</word>
            <lemma>murder</lemma>
            <CharacterOffsetBegin>167</CharacterOffsetBegin>
            <CharacterOffsetEnd>173</CharacterOffsetEnd>
            <POS>NN</POS>
          </token>
          <token id="23">
            <word>following</word>
            <lemma>follow</lemma>
            <CharacterOffsetBegin>174</CharacterOffsetBegin>
            <CharacterOffsetEnd>183</CharacterOffsetEnd>
            <POS>VBG</POS>
          </token>
          <token id="24">
            <word>the</word>
            <lemma>the</lemma>
            <CharacterOffsetBegin>184</CharacterOffsetBegin>
            <CharacterOffsetEnd>187</CharacterOffsetEnd>
            <POS>DT</POS>
          </token>
          <token id="25">
            <word>death</word>
            <lemma>death</lemma>
            <CharacterOffsetBegin>188</CharacterOffsetBegin>
            <CharacterOffsetEnd>193</CharacterOffsetEnd>
            <POS>NN</POS>
          </token>
          <token id="26">
            <word>of</word>
            <lemma>of</lemma>
            <CharacterOffsetBegin>194</CharacterOffsetBegin>
            <CharacterOffsetEnd>196</CharacterOffsetEnd>
            <POS>IN</POS>
          </token>
          <token id="27">
            <word>a</word>
            <lemma>a</lemma>
            <CharacterOffsetBegin>197</CharacterOffsetBegin>
            <CharacterOffsetEnd>198</CharacterOffsetEnd>
            <POS>DT</POS>
          </token>
          <token id="28">
            <word>woman</word>
            <lemma>woman</lemma>
            <CharacterOffsetBegin>199</CharacterOffsetBegin>
            <CharacterOffsetEnd>204</CharacterOffsetEnd>
            <POS>NN</POS>
          </token>
          <token id="29">
            <word>who</word>
            <lemma>who</lemma>
            <CharacterOffsetBegin>205</CharacterOffsetBegin>
            <CharacterOffsetEnd>208</CharacterOffsetEnd>
            <POS>WP</POS>
          </token>
          <token id="30">
            <word>was</word>
            <lemma>be</lemma>
            <CharacterOffsetBegin>209</CharacterOffsetBegin>
            <CharacterOffsetEnd>212</CharacterOffsetEnd>
            <POS>VBD</POS>
          </token>
          <token id="31">
            <word>assaulted</word>
            <lemma>assault</lemma>
            <CharacterOffsetBegin>213</CharacterOffsetBegin>
            <CharacterOffsetEnd>222</CharacterOffsetEnd>
            <POS>VBN</POS>
          </token>
          <token id="32">
            <word>in</word>
            <lemma>in</lemma>
            <CharacterOffsetBegin>223</CharacterOffsetBegin>
            <CharacterOffsetEnd>225</CharacterOffsetEnd>
            <POS>IN</POS>
          </token>
          <token id="33">
            <word>the</word>
            <lemma>the</lemma>
            <CharacterOffsetBegin>226</CharacterOffsetBegin>
            <CharacterOffsetEnd>229</CharacterOffsetEnd>
            <POS>DT</POS>
          </token>
          <token id="34">
            <word>street</word>
            <lemma>street</lemma>
            <CharacterOffsetBegin>230</CharacterOffsetBegin>
            <CharacterOffsetEnd>236</CharacterOffsetEnd>
            <POS>NN</POS>
          </token>
          <token id="35">
            <word>.</word>
            <lemma>.</lemma>
            <CharacterOffsetBegin>236</CharacterOffsetBegin>
            <CharacterOffsetEnd>237</CharacterOffsetEnd>
            <POS>.</POS>
          </token>
        </tokens>
      </sentence>
      <sentence id="2">
        <tokens>
          <token id="1">
            <word>[</word>
            <lemma>[</lemma>
            <CharacterOffsetBegin>239</CharacterOffsetBegin>
            <CharacterOffsetEnd>240</CharacterOffsetEnd>
            <POS>-LRB-</POS>
          </token>
          <token id="2">
            <word>XSUM</word>
            <lemma>XSUM</lemma>
            <CharacterOffsetBegin>240</CharacterOffsetBegin>
            <CharacterOffsetEnd>244</CharacterOffsetEnd>
            <POS>NNP</POS>
          </token>
          <token id="3">
            <word>]</word>
            <lemma>]</lemma>
            <CharacterOffsetBegin>244</CharacterOffsetBegin>
            <CharacterOffsetEnd>245</CharacterOffsetEnd>
            <POS>-RRB-</POS>
          </token>
          <token id="4">
            <word>RESTBODY</word>
            <lemma>RESTBODY</lemma>
            <CharacterOffsetBegin>245</CharacterOffsetBegin>
            <CharacterOffsetEnd>253</CharacterOffsetEnd>
            <POS>NNP</POS>
          </token>
          <token id="5">
            <word>[</word>
            <lemma>[</lemma>
            <CharacterOffsetBegin>253</CharacterOffsetBegin>
            <CharacterOffsetEnd>254</CharacterOffsetEnd>
            <POS>-LRB-</POS>
          </token>
          <token id="6">
            <word>XSUM</word>
            <lemma>XSUM</lemma>
            <CharacterOffsetBegin>254</CharacterOffsetBegin>
            <CharacterOffsetEnd>258</CharacterOffsetEnd>
            <POS>NNP</POS>
          </token>
          <token id="7">
            <word>]</word>
            <lemma>]</lemma>
            <CharacterOffsetBegin>258</CharacterOffsetBegin>
            <CharacterOffsetEnd>259</CharacterOffsetEnd>
            <POS>-RRB-</POS>
          </token>
          <token id="8">
            <word>Share</word>
            <lemma>share</lemma>
            <CharacterOffsetBegin>260</CharacterOffsetBegin>
            <CharacterOffsetEnd>265</CharacterOffsetEnd>
            <POS>VB</POS>
          </token>
          <token id="9">
            <word>this</word>
            <lemma>this</lemma>
            <CharacterOffsetBegin>266</CharacterOffsetBegin>
            <CharacterOffsetEnd>270</CharacterOffsetEnd>
            <POS>DT</POS>
          </token>
          <token id="10">
            <word>with</word>
            <lemma>with</lemma>
            <CharacterOffsetBegin>271</CharacterOffsetBegin>
            <CharacterOffsetEnd>275</CharacterOffsetEnd>
            <POS>IN</POS>
          </token>
          <token id="11">
            <word>Email</word>
            <lemma>email</lemma>
            <CharacterOffsetBegin>276</CharacterOffsetBegin>
            <CharacterOffsetEnd>281</CharacterOffsetEnd>
            <POS>NN</POS>
          </token>
          <token id="12">
            <word>Facebook</word>
            <lemma>Facebook</lemma>
            <CharacterOffsetBegin>282</CharacterOffsetBegin>
            <CharacterOffsetEnd>290</CharacterOffsetEnd>
            <POS>NNP</POS>
          </token>
          <token id="13">
            <word>Messenger</word>
            <lemma>Messenger</lemma>
            <CharacterOffsetBegin>291</CharacterOffsetBegin>
            <CharacterOffsetEnd>300</CharacterOffsetEnd>
            <POS>NNP</POS>
          </token>
          <token id="14">
            <word>Messenger</word>
            <lemma>Messenger</lemma>
            <CharacterOffsetBegin>301</CharacterOffsetBegin>
            <CharacterOffsetEnd>310</CharacterOffsetEnd>
            <POS>NNP</POS>
          </token>
          <token id="15">
            <word>Twitter</word>
            <lemma>Twitter</lemma>
            <CharacterOffsetBegin>311</CharacterOffsetBegin>
            <CharacterOffsetEnd>318</CharacterOffsetEnd>
            <POS>NNP</POS>
          </token>
          <token id="16">
            <word>Pinterest</word>
            <lemma>Pinterest</lemma>
            <CharacterOffsetBegin>319</CharacterOffsetBegin>
            <CharacterOffsetEnd>328</CharacterOffsetEnd>
            <POS>NNP</POS>
          </token>
          <token id="17">
            <word>WhatsApp</word>
            <lemma>WhatsApp</lemma>
            <CharacterOffsetBegin>329</CharacterOffsetBegin>
            <CharacterOffsetEnd>337</CharacterOffsetEnd>
            <POS>NNP</POS>
          </token>
          <token id="18">
            <word>LinkedIn</word>
            <lemma>LinkedIn</lemma>
            <CharacterOffsetBegin>338</CharacterOffsetBegin>
            <CharacterOffsetEnd>346</CharacterOffsetEnd>
            <POS>NNP</POS>
          </token>
          <token id="19">
            <word>Copy</word>
            <lemma>copy</lemma>
            <CharacterOffsetBegin>347</CharacterOffsetBegin>
            <CharacterOffsetEnd>351</CharacterOffsetEnd>
            <POS>VB</POS>
          </token>
          <token id="20">
            <word>this</word>
            <lemma>this</lemma>
            <CharacterOffsetBegin>352</CharacterOffsetBegin>
            <CharacterOffsetEnd>356</CharacterOffsetEnd>
            <POS>DT</POS>
          </token>
          <token id="21">
            <word>link</word>
            <lemma>link</lemma>
            <CharacterOffsetBegin>357</CharacterOffsetBegin>
            <CharacterOffsetEnd>361</CharacterOffsetEnd>
            <POS>NN</POS>
          </token>
          <token id="22">
            <word>These</word>
            <lemma>these</lemma>
            <CharacterOffsetBegin>362</CharacterOffsetBegin>
            <CharacterOffsetEnd>367</CharacterOffsetEnd>
            <POS>DT</POS>
          </token>
          <token id="23">
            <word>are</word>
            <lemma>be</lemma>
            <CharacterOffsetBegin>368</CharacterOffsetBegin>
            <CharacterOffsetEnd>371</CharacterOffsetEnd>
            <POS>VBP</POS>
          </token>
          <token id="24">
            <word>external</word>
            <lemma>external</lemma>
            <CharacterOffsetBegin>372</CharacterOffsetBegin>
            <CharacterOffsetEnd>380</CharacterOffsetEnd>
            <POS>JJ</POS>
          </token>
          <token id="25">
            <word>links</word>
            <lemma>link</lemma>
            <CharacterOffsetBegin>381</CharacterOffsetBegin>
            <CharacterOffsetEnd>386</CharacterOffsetEnd>
            <POS>NNS</POS>
          </token>
          <token id="26">
            <word>and</word>
            <lemma>and</lemma>
            <CharacterOffsetBegin>387</CharacterOffsetBegin>
            <CharacterOffsetEnd>390</CharacterOffsetEnd>
            <POS>CC</POS>
          </token>
          <token id="27">
            <word>will</word>
            <lemma>will</lemma>
            <CharacterOffsetBegin>391</CharacterOffsetBegin>
            <CharacterOffsetEnd>395</CharacterOffsetEnd>
            <POS>MD</POS>
          </token>
          <token id="28">
            <word>open</word>
            <lemma>open</lemma>
            <CharacterOffsetBegin>396</CharacterOffsetBegin>
            <CharacterOffsetEnd>400</CharacterOffsetEnd>
            <POS>VB</POS>
          </token>
          <token id="29">
            <word>in</word>
            <lemma>in</lemma>
            <CharacterOffsetBegin>401</CharacterOffsetBegin>
            <CharacterOffsetEnd>403</CharacterOffsetEnd>
            <POS>IN</POS>
          </token>
          <token id="30">
            <word>a</word>
            <lemma>a</lemma>
            <CharacterOffsetBegin>404</CharacterOffsetBegin>
            <CharacterOffsetEnd>405</CharacterOffsetEnd>
            <POS>DT</POS>
          </token>
          <token id="31">
            <word>new</word>
            <lemma>new</lemma>
            <CharacterOffsetBegin>406</CharacterOffsetBegin>
            <CharacterOffsetEnd>409</CharacterOffsetEnd>
            <POS>JJ</POS>
          </token>
          <token id="32">
            <word>window</word>
            <lemma>window</lemma>
            <CharacterOffsetBegin>410</CharacterOffsetBegin>
            <CharacterOffsetEnd>416</CharacterOffsetEnd>
            <POS>NN</POS>
          </token>
          <token id="33">
            <word>Joanne</word>
            <lemma>Joanne</lemma>
            <CharacterOffsetBegin>417</CharacterOffsetBegin>
            <CharacterOffsetEnd>423</CharacterOffsetEnd>
            <POS>NNP</POS>
          </token>
          <token id="34">
            <word>Hemingway</word>
            <lemma>Hemingway</lemma>
            <CharacterOffsetBegin>424</CharacterOffsetBegin>
            <CharacterOffsetEnd>433</CharacterOffsetEnd>
            <POS>NNP</POS>
          </token>
          <token id="35">
            <word>,</word>
            <lemma>,</lemma>
            <CharacterOffsetBegin>433</CharacterOffsetBegin>
            <CharacterOffsetEnd>434</CharacterOffsetEnd>
            <POS>,</POS>
          </token>
          <token id="36">
            <word>39</word>
            <lemma>39</lemma>
            <CharacterOffsetBegin>435</CharacterOffsetBegin>
            <CharacterOffsetEnd>437</CharacterOffsetEnd>
            <POS>CD</POS>
          </token>
          <token id="37">
            <word>,</word>
            <lemma>,</lemma>
            <CharacterOffsetBegin>437</CharacterOffsetBegin>
            <CharacterOffsetEnd>438</CharacterOffsetEnd>
            <POS>,</POS>
          </token>
          <token id="38">
            <word>was</word>
            <lemma>be</lemma>
            <CharacterOffsetBegin>439</CharacterOffsetBegin>
            <CharacterOffsetEnd>442</CharacterOffsetEnd>
            <POS>VBD</POS>
          </token>
          <token id="39">
            <word>attacked</word>
            <lemma>attack</lemma>
            <CharacterOffsetBegin>443</CharacterOffsetBegin>
            <CharacterOffsetEnd>451</CharacterOffsetEnd>
            <POS>VBN</POS>
          </token>
          <token id="40">
            <word>outside</word>
            <lemma>outside</lemma>
            <CharacterOffsetBegin>452</CharacterOffsetBegin>
            <CharacterOffsetEnd>459</CharacterOffsetEnd>
            <POS>IN</POS>
          </token>
          <token id="41">
            <word>of</word>
            <lemma>of</lemma>
            <CharacterOffsetBegin>460</CharacterOffsetBegin>
            <CharacterOffsetEnd>462</CharacterOffsetEnd>
            <POS>IN</POS>
          </token>
          <token id="42">
            <word>a</word>
            <lemma>a</lemma>
            <CharacterOffsetBegin>463</CharacterOffsetBegin>
            <CharacterOffsetEnd>464</CharacterOffsetEnd>
            <POS>DT</POS>
          </token>
          <token id="43">
            <word>flat</word>
            <lemma>flat</lemma>
            <CharacterOffsetBegin>465</CharacterOffsetBegin>
            <CharacterOffsetEnd>469</CharacterOffsetEnd>
            <POS>JJ</POS>
          </token>
          <token id="44">
            <word>on</word>
            <lemma>on</lemma>
            <CharacterOffsetBegin>470</CharacterOffsetBegin>
            <CharacterOffsetEnd>472</CharacterOffsetEnd>
            <POS>IN</POS>
          </token>
          <token id="45">
            <word>Beverley</word>
            <lemma>Beverley</lemma>
            <CharacterOffsetBegin>473</CharacterOffsetBegin>
            <CharacterOffsetEnd>481</CharacterOffsetEnd>
            <POS>NNP</POS>
          </token>
          <token id="46">
            <word>Road</word>
            <lemma>Road</lemma>
            <CharacterOffsetBegin>482</CharacterOffsetBegin>
            <CharacterOffsetEnd>486</CharacterOffsetEnd>
            <POS>NNP</POS>
          </token>
          <token id="47">
            <word>,</word>
            <lemma>,</lemma>
            <CharacterOffsetBegin>486</CharacterOffsetBegin>
            <CharacterOffsetEnd>487</CharacterOffsetEnd>
            <POS>,</POS>
          </token>
          <token id="48">
            <word>Hull</word>
            <lemma>Hull</lemma>
            <CharacterOffsetBegin>488</CharacterOffsetBegin>
            <CharacterOffsetEnd>492</CharacterOffsetEnd>
            <POS>NNP</POS>
          </token>
          <token id="49">
            <word>on</word>
            <lemma>on</lemma>
            <CharacterOffsetBegin>493</CharacterOffsetBegin>
            <CharacterOffsetEnd>495</CharacterOffsetEnd>
            <POS>IN</POS>
          </token>
          <token id="50">
            <word>29</word>
            <lemma>29</lemma>
            <CharacterOffsetBegin>496</CharacterOffsetBegin>
            <CharacterOffsetEnd>498</CharacterOffsetEnd>
            <POS>CD</POS>
          </token>
          <token id="51">
            <word>June</word>
            <lemma>June</lemma>
            <CharacterOffsetBegin>499</CharacterOffsetBegin>
            <CharacterOffsetEnd>503</CharacterOffsetEnd>
            <POS>NNP</POS>
          </token>
          <token id="52">
            <word>.</word>
            <lemma>.</lemma>
            <CharacterOffsetBegin>503</CharacterOffsetBegin>
            <CharacterOffsetEnd>504</CharacterOffsetEnd>
            <POS>.</POS>
          </token>
        </tokens>
      </sentence>
      <sentence id="3">
        <tokens>
          <token id="1">
            <word>She</word>
            <lemma>she</lemma>
            <CharacterOffsetBegin>505</CharacterOffsetBegin>
            <CharacterOffsetEnd>508</CharacterOffsetEnd>
            <POS>PRP</POS>
          </token>
          <token id="2">
            <word>suffered</word>
            <lemma>suffer</lemma>
            <CharacterOffsetBegin>509</CharacterOffsetBegin>
            <CharacterOffsetEnd>517</CharacterOffsetEnd>
            <POS>VBD</POS>
          </token>
          <token id="3">
            <word>"</word>
            <lemma>"</lemma>
            <CharacterOffsetBegin>518</CharacterOffsetBegin>
            <CharacterOffsetEnd>519</CharacterOffsetEnd>
            <POS>``</POS>
          </token>
          <token id="4">
            <word>serious</word>
            <lemma>serious</lemma>
            <CharacterOffsetBegin>519</CharacterOffsetBegin>
            <CharacterOffsetEnd>526</CharacterOffsetEnd>
            <POS>JJ</POS>
          </token>
          <token id="5">
            <word>injuries</word>
            <lemma>injury</lemma>
            <CharacterOffsetBegin>527</CharacterOffsetBegin>
            <CharacterOffsetEnd>535</CharacterOffsetEnd>
            <POS>NNS</POS>
          </token>
          <token id="6">
            <word>"</word>
            <lemma>"</lemma>
            <CharacterOffsetBegin>535</CharacterOffsetBegin>
            <CharacterOffsetEnd>536</CharacterOffsetEnd>
            <POS>''</POS>
          </token>
          <token id="7">
            <word>and</word>
            <lemma>and</lemma>
            <CharacterOffsetBegin>537</CharacterOffsetBegin>
            <CharacterOffsetEnd>540</CharacterOffsetEnd>
            <POS>CC</POS>
          </token>
          <token id="8">
            <word>later</word>
            <lemma>later</lemma>
            <CharacterOffsetBegin>541</CharacterOffsetBegin>
            <CharacterOffsetEnd>546</CharacterOffsetEnd>
            <POS>RB</POS>
          </token>
          <token id="9">
            <word>died</word>
            <lemma>die</lemma>
            <CharacterOffsetBegin>547</CharacterOffsetBegin>
            <CharacterOffsetEnd>551</CharacterOffsetEnd>
            <POS>VBD</POS>
          </token>
          <token id="10">
            <word>in</word>
            <lemma>in</lemma>
            <CharacterOffsetBegin>552</CharacterOffsetBegin>
            <CharacterOffsetEnd>554</CharacterOffsetEnd>
            <POS>IN</POS>
          </token>
          <token id="11">
            <word>hospital</word>
            <lemma>hospital</lemma>
            <CharacterOffsetBegin>555</CharacterOffsetBegin>
            <CharacterOffsetEnd>563</CharacterOffsetEnd>
            <POS>NN</POS>
          </token>
          <token id="12">
            <word>.</word>
            <lemma>.</lemma>
            <CharacterOffsetBegin>563</CharacterOffsetBegin>
            <CharacterOffsetEnd>564</CharacterOffsetEnd>
            <POS>.</POS>
          </token>
        </tokens>
      </sentence>
      <sentence id="4">
        <tokens>
          <token id="1">
            <word>Angela</word>
            <lemma>Angela</lemma>
            <CharacterOffsetBegin>565</CharacterOffsetBegin>
            <CharacterOffsetEnd>571</CharacterOffsetEnd>
            <POS>NNP</POS>
          </token>
          <token id="2">
            <word>Burkitt</word>
            <lemma>Burkitt</lemma>
            <CharacterOffsetBegin>572</CharacterOffsetBegin>
            <CharacterOffsetEnd>579</CharacterOffsetEnd>
            <POS>NNP</POS>
          </token>
          <token id="3">
            <word>53</word>
            <lemma>53</lemma>
            <CharacterOffsetBegin>580</CharacterOffsetBegin>
            <CharacterOffsetEnd>582</CharacterOffsetEnd>
            <POS>CD</POS>
          </token>
          <token id="4">
            <word>,</word>
            <lemma>,</lemma>
            <CharacterOffsetBegin>582</CharacterOffsetBegin>
            <CharacterOffsetEnd>583</CharacterOffsetEnd>
            <POS>,</POS>
          </token>
          <token id="5">
            <word>also</word>
            <lemma>also</lemma>
            <CharacterOffsetBegin>584</CharacterOffsetBegin>
            <CharacterOffsetEnd>588</CharacterOffsetEnd>
            <POS>RB</POS>
          </token>
          <token id="6">
            <word>of</word>
            <lemma>of</lemma>
            <CharacterOffsetBegin>589</CharacterOffsetBegin>
            <CharacterOffsetEnd>591</CharacterOffsetEnd>
            <POS>IN</POS>
          </token>
          <token id="7">
            <word>Beverley</word>
            <lemma>Beverley</lemma>
            <CharacterOffsetBegin>592</CharacterOffsetBegin>
            <CharacterOffsetEnd>600</CharacterOffsetEnd>
            <POS>NNP</POS>
          </token>
          <token id="8">
            <word>Road</word>
            <lemma>Road</lemma>
            <CharacterOffsetBegin>601</CharacterOffsetBegin>
            <CharacterOffsetEnd>605</CharacterOffsetEnd>
            <POS>NNP</POS>
          </token>
          <token id="9">
            <word>,</word>
            <lemma>,</lemma>
            <CharacterOffsetBegin>605</CharacterOffsetBegin>
            <CharacterOffsetEnd>606</CharacterOffsetEnd>
            <POS>,</POS>
          </token>
          <token id="10">
            <word>appeared</word>
            <lemma>appear</lemma>
            <CharacterOffsetBegin>607</CharacterOffsetBegin>
            <CharacterOffsetEnd>615</CharacterOffsetEnd>
            <POS>VBD</POS>
          </token>
          <token id="11">
            <word>at</word>
            <lemma>at</lemma>
            <CharacterOffsetBegin>616</CharacterOffsetBegin>
            <CharacterOffsetEnd>618</CharacterOffsetEnd>
            <POS>IN</POS>
          </token>
          <token id="12">
            <word>the</word>
            <lemma>the</lemma>
            <CharacterOffsetBegin>619</CharacterOffsetBegin>
            <CharacterOffsetEnd>622</CharacterOffsetEnd>
            <POS>DT</POS>
          </token>
          <token id="13">
            <word>city</word>
            <lemma>city</lemma>
            <CharacterOffsetBegin>623</CharacterOffsetBegin>
            <CharacterOffsetEnd>627</CharacterOffsetEnd>
            <POS>NN</POS>
          </token>
          <token id="14">
            <word>'s</word>
            <lemma>'s</lemma>
            <CharacterOffsetBegin>627</CharacterOffsetBegin>
            <CharacterOffsetEnd>629</CharacterOffsetEnd>
            <POS>POS</POS>
          </token>
          <token id="15">
            <word>magistrates</word>
            <lemma>magistrate</lemma>
            <CharacterOffsetBegin>630</CharacterOffsetBegin>
            <CharacterOffsetEnd>641</CharacterOffsetEnd>
            <POS>NNS</POS>
          </token>
          <token id="16">
            <word>'</word>
            <lemma>'</lemma>
            <CharacterOffsetBegin>641</CharacterOffsetBegin>
            <CharacterOffsetEnd>642</CharacterOffsetEnd>
            <POS>POS</POS>
          </token>
          <token id="17">
            <word>court</word>
            <lemma>court</lemma>
            <CharacterOffsetBegin>643</CharacterOffsetBegin>
            <CharacterOffsetEnd>648</CharacterOffsetEnd>
            <POS>NN</POS>
          </token>
          <token id="18">
            <word>earlier</word>
            <lemma>earlier</lemma>
            <CharacterOffsetBegin>649</CharacterOffsetBegin>
            <CharacterOffsetEnd>656</CharacterOffsetEnd>
            <POS>RBR</POS>
          </token>
          <token id="19">
            <word>accused</word>
            <lemma>accuse</lemma>
            <CharacterOffsetBegin>657</CharacterOffsetBegin>
            <CharacterOffsetEnd>664</CharacterOffsetEnd>
            <POS>VBN</POS>
          </token>
          <token id="20">
            <word>of</word>
            <lemma>of</lemma>
            <CharacterOffsetBegin>665</CharacterOffsetBegin>
            <CharacterOffsetEnd>667</CharacterOffsetEnd>
            <POS>IN</POS>
          </token>
          <token id="21">
            <word>murder</word>
            <lemma>murder</lemma>
            <CharacterOffsetBegin>668</CharacterOffsetBegin>
            <CharacterOffsetEnd>674</CharacterOffsetEnd>
            <POS>NN</POS>
          </token>
          <token id="22">
            <word>.</word>
            <lemma>.</lemma>
            <CharacterOffsetBegin>674</CharacterOffsetBegin>
            <CharacterOffsetEnd>675</CharacterOffsetEnd>
            <POS>.</POS>
          </token>
        </tokens>
      </sentence>
      <sentence id="5">
        <tokens>
          <token id="1">
            <word>She</word>
            <lemma>she</lemma>
            <CharacterOffsetBegin>676</CharacterOffsetBegin>
            <CharacterOffsetEnd>679</CharacterOffsetEnd>
            <POS>PRP</POS>
          </token>
          <token id="2">
            <word>was</word>
            <lemma>be</lemma>
            <CharacterOffsetBegin>680</CharacterOffsetBegin>
            <CharacterOffsetEnd>683</CharacterOffsetEnd>
            <POS>VBD</POS>
          </token>
          <token id="3">
            <word>remanded</word>
            <lemma>remand</lemma>
            <CharacterOffsetBegin>684</CharacterOffsetBegin>
            <CharacterOffsetEnd>692</CharacterOffsetEnd>
            <POS>VBN</POS>
          </token>
          <token id="4">
            <word>in</word>
            <lemma>in</lemma>
            <CharacterOffsetBegin>693</CharacterOffsetBegin>
            <CharacterOffsetEnd>695</CharacterOffsetEnd>
            <POS>IN</POS>
          </token>
          <token id="5">
            <word>custody</word>
            <lemma>custody</lemma>
            <CharacterOffsetBegin>696</CharacterOffsetBegin>
            <CharacterOffsetEnd>703</CharacterOffsetEnd>
            <POS>NN</POS>
          </token>
          <token id="6">
            <word>to</word>
            <lemma>to</lemma>
            <CharacterOffsetBegin>704</CharacterOffsetBegin>
            <CharacterOffsetEnd>706</CharacterOffsetEnd>
            <POS>TO</POS>
          </token>
          <token id="7">
            <word>appear</word>
            <lemma>appear</lemma>
            <CharacterOffsetBegin>707</CharacterOffsetBegin>
            <CharacterOffsetEnd>713</CharacterOffsetEnd>
            <POS>VB</POS>
          </token>
          <token id="8">
            <word>at</word>
            <lemma>at</lemma>
            <CharacterOffsetBegin>714</CharacterOffsetBegin>
            <CharacterOffsetEnd>716</CharacterOffsetEnd>
            <POS>IN</POS>
          </token>
          <token id="9">
            <word>Hull</word>
            <lemma>Hull</lemma>
            <CharacterOffsetBegin>717</CharacterOffsetBegin>
            <CharacterOffsetEnd>721</CharacterOffsetEnd>
            <POS>NNP</POS>
          </token>
          <token id="10">
            <word>Crown</word>
            <lemma>Crown</lemma>
            <CharacterOffsetBegin>722</CharacterOffsetBegin>
            <CharacterOffsetEnd>727</CharacterOffsetEnd>
            <POS>NNP</POS>
          </token>
          <token id="11">
            <word>Court</word>
            <lemma>Court</lemma>
            <CharacterOffsetBegin>728</CharacterOffsetBegin>
            <CharacterOffsetEnd>733</CharacterOffsetEnd>
            <POS>NNP</POS>
          </token>
          <token id="12">
            <word>on</word>
            <lemma>on</lemma>
            <CharacterOffsetBegin>734</CharacterOffsetBegin>
            <CharacterOffsetEnd>736</CharacterOffsetEnd>
            <POS>IN</POS>
          </token>
          <token id="13">
            <word>Friday</word>
            <lemma>Friday</lemma>
            <CharacterOffsetBegin>737</CharacterOffsetBegin>
            <CharacterOffsetEnd>743</CharacterOffsetEnd>
            <POS>NNP</POS>
          </token>
          <token id="14">
            <word>.</word>
            <lemma>.</lemma>
            <CharacterOffsetBegin>743</CharacterOffsetBegin>
            <CharacterOffsetEnd>744</CharacterOffsetEnd>
            <POS>.</POS>
          </token>
        </tokens>
      </sentence>
      <sentence id="6">
        <tokens>
          <token id="1">
            <word>More</word>
            <lemma>more</lemma>
            <CharacterOffsetBegin>745</CharacterOffsetBegin>
            <CharacterOffsetEnd>749</CharacterOffsetEnd>
            <POS>JJR</POS>
          </token>
          <token id="2">
            <word>on</word>
            <lemma>on</lemma>
            <CharacterOffsetBegin>750</CharacterOffsetBegin>
            <CharacterOffsetEnd>752</CharacterOffsetEnd>
            <POS>IN</POS>
          </token>
          <token id="3">
            <word>this</word>
            <lemma>this</lemma>
            <CharacterOffsetBegin>753</CharacterOffsetBegin>
            <CharacterOffsetEnd>757</CharacterOffsetEnd>
            <POS>DT</POS>
          </token>
          <token id="4">
            <word>and</word>
            <lemma>and</lemma>
            <CharacterOffsetBegin>758</CharacterOffsetBegin>
            <CharacterOffsetEnd>761</CharacterOffsetEnd>
            <POS>CC</POS>
          </token>
          <token id="5">
            <word>other</word>
            <lemma>other</lemma>
            <CharacterOffsetBegin>762</CharacterOffsetBegin>
            <CharacterOffsetEnd>767</CharacterOffsetEnd>
            <POS>JJ</POS>
          </token>
          <token id="6">
            <word>Hull</word>
            <lemma>Hull</lemma>
            <CharacterOffsetBegin>768</CharacterOffsetBegin>
            <CharacterOffsetEnd>772</CharacterOffsetEnd>
            <POS>NNP</POS>
          </token>
          <token id="7">
            <word>stories</word>
            <lemma>story</lemma>
            <CharacterOffsetBegin>773</CharacterOffsetBegin>
            <CharacterOffsetEnd>780</CharacterOffsetEnd>
            <POS>NNS</POS>
          </token>
          <token id="8">
            <word>Glenn</word>
            <lemma>Glenn</lemma>
            <CharacterOffsetBegin>781</CharacterOffsetBegin>
            <CharacterOffsetEnd>786</CharacterOffsetEnd>
            <POS>NNP</POS>
          </token>
          <token id="9">
            <word>Foster</word>
            <lemma>Foster</lemma>
            <CharacterOffsetBegin>787</CharacterOffsetBegin>
            <CharacterOffsetEnd>793</CharacterOffsetEnd>
            <POS>NNP</POS>
          </token>
          <token id="10">
            <word>,</word>
            <lemma>,</lemma>
            <CharacterOffsetBegin>793</CharacterOffsetBegin>
            <CharacterOffsetEnd>794</CharacterOffsetEnd>
            <POS>,</POS>
          </token>
          <token id="11">
            <word>42</word>
            <lemma>42</lemma>
            <CharacterOffsetBegin>795</CharacterOffsetBegin>
            <CharacterOffsetEnd>797</CharacterOffsetEnd>
            <POS>CD</POS>
          </token>
          <token id="12">
            <word>,</word>
            <lemma>,</lemma>
            <CharacterOffsetBegin>797</CharacterOffsetBegin>
            <CharacterOffsetEnd>798</CharacterOffsetEnd>
            <POS>,</POS>
          </token>
          <token id="13">
            <word>of</word>
            <lemma>of</lemma>
            <CharacterOffsetBegin>799</CharacterOffsetBegin>
            <CharacterOffsetEnd>801</CharacterOffsetEnd>
            <POS>IN</POS>
          </token>
          <token id="14">
            <word>Beverley</word>
            <lemma>Beverley</lemma>
            <CharacterOffsetBegin>802</CharacterOffsetBegin>
            <CharacterOffsetEnd>810</CharacterOffsetEnd>
            <POS>NNP</POS>
          </token>
          <token id="15">
            <word>Road</word>
            <lemma>Road</lemma>
            <CharacterOffsetBegin>811</CharacterOffsetBegin>
            <CharacterOffsetEnd>815</CharacterOffsetEnd>
            <POS>NNP</POS>
          </token>
          <token id="16">
            <word>,</word>
            <lemma>,</lemma>
            <CharacterOffsetBegin>815</CharacterOffsetBegin>
            <CharacterOffsetEnd>816</CharacterOffsetEnd>
            <POS>,</POS>
          </token>
          <token id="17">
            <word>Hull</word>
            <lemma>Hull</lemma>
            <CharacterOffsetBegin>817</CharacterOffsetBegin>
            <CharacterOffsetEnd>821</CharacterOffsetEnd>
            <POS>NNP</POS>
          </token>
          <token id="18">
            <word>who</word>
            <lemma>who</lemma>
            <CharacterOffsetBegin>822</CharacterOffsetBegin>
            <CharacterOffsetEnd>825</CharacterOffsetEnd>
            <POS>WP</POS>
          </token>
          <token id="19">
            <word>was</word>
            <lemma>be</lemma>
            <CharacterOffsetBegin>826</CharacterOffsetBegin>
            <CharacterOffsetEnd>829</CharacterOffsetEnd>
            <POS>VBD</POS>
          </token>
          <token id="20">
            <word>previously</word>
            <lemma>previously</lemma>
            <CharacterOffsetBegin>830</CharacterOffsetBegin>
            <CharacterOffsetEnd>840</CharacterOffsetEnd>
            <POS>RB</POS>
          </token>
          <token id="21">
            <word>charged</word>
            <lemma>charge</lemma>
            <CharacterOffsetBegin>841</CharacterOffsetBegin>
            <CharacterOffsetEnd>848</CharacterOffsetEnd>
            <POS>VBN</POS>
          </token>
          <token id="22">
            <word>with</word>
            <lemma>with</lemma>
            <CharacterOffsetBegin>849</CharacterOffsetBegin>
            <CharacterOffsetEnd>853</CharacterOffsetEnd>
            <POS>IN</POS>
          </token>
          <token id="23">
            <word>Ms</word>
            <lemma>Ms</lemma>
            <CharacterOffsetBegin>854</CharacterOffsetBegin>
            <CharacterOffsetEnd>856</CharacterOffsetEnd>
            <POS>NNPS</POS>
          </token>
          <token id="24">
            <word>Hemingway</word>
            <lemma>Hemingway</lemma>
            <CharacterOffsetBegin>857</CharacterOffsetBegin>
            <CharacterOffsetEnd>866</CharacterOffsetEnd>
            <POS>NNP</POS>
          </token>
          <token id="25">
            <word>'s</word>
            <lemma>'s</lemma>
            <CharacterOffsetBegin>866</CharacterOffsetBegin>
            <CharacterOffsetEnd>868</CharacterOffsetEnd>
            <POS>POS</POS>
          </token>
          <token id="26">
            <word>murder</word>
            <lemma>murder</lemma>
            <CharacterOffsetBegin>869</CharacterOffsetBegin>
            <CharacterOffsetEnd>875</CharacterOffsetEnd>
            <POS>NN</POS>
          </token>
          <token id="27">
            <word>has</word>
            <lemma>have</lemma>
            <CharacterOffsetBegin>876</CharacterOffsetBegin>
            <CharacterOffsetEnd>879</CharacterOffsetEnd>
            <POS>VBZ</POS>
          </token>
          <token id="28">
            <word>had</word>
            <lemma>have</lemma>
            <CharacterOffsetBegin>880</CharacterOffsetBegin>
            <CharacterOffsetEnd>883</CharacterOffsetEnd>
            <POS>VBN</POS>
          </token>
          <token id="29">
            <word>the</word>
            <lemma>the</lemma>
            <CharacterOffsetBegin>884</CharacterOffsetBegin>
            <CharacterOffsetEnd>887</CharacterOffsetEnd>
            <POS>DT</POS>
          </token>
          <token id="30">
            <word>charge</word>
            <lemma>charge</lemma>
            <CharacterOffsetBegin>888</CharacterOffsetBegin>
            <CharacterOffsetEnd>894</CharacterOffsetEnd>
            <POS>NN</POS>
          </token>
          <token id="31">
            <word>against</word>
            <lemma>against</lemma>
            <CharacterOffsetBegin>895</CharacterOffsetBegin>
            <CharacterOffsetEnd>902</CharacterOffsetEnd>
            <POS>IN</POS>
          </token>
          <token id="32">
            <word>him</word>
            <lemma>he</lemma>
            <CharacterOffsetBegin>903</CharacterOffsetBegin>
            <CharacterOffsetEnd>906</CharacterOffsetEnd>
            <POS>PRP</POS>
          </token>
          <token id="33">
            <word>dropped</word>
            <lemma>drop</lemma>
            <CharacterOffsetBegin>907</CharacterOffsetBegin>
            <CharacterOffsetEnd>914</CharacterOffsetEnd>
            <POS>VBD</POS>
          </token>
          <token id="34">
            <word>by</word>
            <lemma>by</lemma>
            <CharacterOffsetBegin>915</CharacterOffsetBegin>
            <CharacterOffsetEnd>917</CharacterOffsetEnd>
            <POS>IN</POS>
          </token>
          <token id="35">
            <word>the</word>
            <lemma>the</lemma>
            <CharacterOffsetBegin>918</CharacterOffsetBegin>
            <CharacterOffsetEnd>921</CharacterOffsetEnd>
            <POS>DT</POS>
          </token>
          <token id="36">
            <word>Crown</word>
            <lemma>Crown</lemma>
            <CharacterOffsetBegin>922</CharacterOffsetBegin>
            <CharacterOffsetEnd>927</CharacterOffsetEnd>
            <POS>NNP</POS>
          </token>
          <token id="37">
            <word>Prosecution</word>
            <lemma>Prosecution</lemma>
            <CharacterOffsetBegin>928</CharacterOffsetBegin>
            <CharacterOffsetEnd>939</CharacterOffsetEnd>
            <POS>NNP</POS>
          </token>
          <token id="38">
            <word>Service</word>
            <lemma>Service</lemma>
            <CharacterOffsetBegin>940</CharacterOffsetBegin>
            <CharacterOffsetEnd>947</CharacterOffsetEnd>
            <POS>NNP</POS>
          </token>
          <token id="39">
            <word>.</word>
            <lemma>.</lemma>
            <CharacterOffsetBegin>947</CharacterOffsetBegin>
            <CharacterOffsetEnd>948</CharacterOffsetEnd>
            <POS>.</POS>
          </token>
        </tokens>
      </sentence>
      <sentence id="7">
        <tokens>
          <token id="1">
            <word>Foster</word>
            <lemma>Foster</lemma>
            <CharacterOffsetBegin>949</CharacterOffsetBegin>
            <CharacterOffsetEnd>955</CharacterOffsetEnd>
            <POS>NNP</POS>
          </token>
          <token id="2">
            <word>appeared</word>
            <lemma>appear</lemma>
            <CharacterOffsetBegin>956</CharacterOffsetBegin>
            <CharacterOffsetEnd>964</CharacterOffsetEnd>
            <POS>VBD</POS>
          </token>
          <token id="3">
            <word>at</word>
            <lemma>at</lemma>
            <CharacterOffsetBegin>965</CharacterOffsetBegin>
            <CharacterOffsetEnd>967</CharacterOffsetEnd>
            <POS>IN</POS>
          </token>
          <token id="4">
            <word>Hull</word>
            <lemma>Hull</lemma>
            <CharacterOffsetBegin>968</CharacterOffsetBegin>
            <CharacterOffsetEnd>972</CharacterOffsetEnd>
            <POS>NNP</POS>
          </token>
          <token id="5">
            <word>Crown</word>
            <lemma>Crown</lemma>
            <CharacterOffsetBegin>973</CharacterOffsetBegin>
            <CharacterOffsetEnd>978</CharacterOffsetEnd>
            <POS>NNP</POS>
          </token>
          <token id="6">
            <word>Court</word>
            <lemma>Court</lemma>
            <CharacterOffsetBegin>979</CharacterOffsetBegin>
            <CharacterOffsetEnd>984</CharacterOffsetEnd>
            <POS>NNP</POS>
          </token>
          <token id="7">
            <word>on</word>
            <lemma>on</lemma>
            <CharacterOffsetBegin>985</CharacterOffsetBegin>
            <CharacterOffsetEnd>987</CharacterOffsetEnd>
            <POS>IN</POS>
          </token>
          <token id="8">
            <word>Monday</word>
            <lemma>Monday</lemma>
            <CharacterOffsetBegin>988</CharacterOffsetBegin>
            <CharacterOffsetEnd>994</CharacterOffsetEnd>
            <POS>NNP</POS>
          </token>
          <token id="9">
            <word>and</word>
            <lemma>and</lemma>
            <CharacterOffsetBegin>995</CharacterOffsetBegin>
            <CharacterOffsetEnd>998</CharacterOffsetEnd>
            <POS>CC</POS>
          </token>
          <token id="10">
            <word>pleaded</word>
            <lemma>plead</lemma>
            <CharacterOffsetBegin>999</CharacterOffsetBegin>
            <CharacterOffsetEnd>1006</CharacterOffsetEnd>
            <POS>VBD</POS>
          </token>
          <token id="11">
            <word>guilty</word>
            <lemma>guilty</lemma>
            <CharacterOffsetBegin>1007</CharacterOffsetBegin>
            <CharacterOffsetEnd>1013</CharacterOffsetEnd>
            <POS>JJ</POS>
          </token>
          <token id="12">
            <word>to</word>
            <lemma>to</lemma>
            <CharacterOffsetBegin>1014</CharacterOffsetBegin>
            <CharacterOffsetEnd>1016</CharacterOffsetEnd>
            <POS>IN</POS>
          </token>
          <token id="13">
            <word>affray</word>
            <lemma>affray</lemma>
            <CharacterOffsetBegin>1017</CharacterOffsetBegin>
            <CharacterOffsetEnd>1023</CharacterOffsetEnd>
            <POS>NN</POS>
          </token>
          <token id="14">
            <word>,</word>
            <lemma>,</lemma>
            <CharacterOffsetBegin>1023</CharacterOffsetBegin>
            <CharacterOffsetEnd>1024</CharacterOffsetEnd>
            <POS>,</POS>
          </token>
          <token id="15">
            <word>being</word>
            <lemma>be</lemma>
            <CharacterOffsetBegin>1025</CharacterOffsetBegin>
            <CharacterOffsetEnd>1030</CharacterOffsetEnd>
            <POS>VBG</POS>
          </token>
          <token id="16">
            <word>in</word>
            <lemma>in</lemma>
            <CharacterOffsetBegin>1031</CharacterOffsetBegin>
            <CharacterOffsetEnd>1033</CharacterOffsetEnd>
            <POS>IN</POS>
          </token>
          <token id="17">
            <word>possession</word>
            <lemma>possession</lemma>
            <CharacterOffsetBegin>1034</CharacterOffsetBegin>
            <CharacterOffsetEnd>1044</CharacterOffsetEnd>
            <POS>NN</POS>
          </token>
          <token id="18">
            <word>of</word>
            <lemma>of</lemma>
            <CharacterOffsetBegin>1045</CharacterOffsetBegin>
            <CharacterOffsetEnd>1047</CharacterOffsetEnd>
            <POS>IN</POS>
          </token>
          <token id="19">
            <word>an</word>
            <lemma>a</lemma>
            <CharacterOffsetBegin>1048</CharacterOffsetBegin>
            <CharacterOffsetEnd>1050</CharacterOffsetEnd>
            <POS>DT</POS>
          </token>
          <token id="20">
            <word>offensive</word>
            <lemma>offensive</lemma>
            <CharacterOffsetBegin>1051</CharacterOffsetBegin>
            <CharacterOffsetEnd>1060</CharacterOffsetEnd>
            <POS>JJ</POS>
          </token>
          <token id="21">
            <word>weapon</word>
            <lemma>weapon</lemma>
            <CharacterOffsetBegin>1061</CharacterOffsetBegin>
            <CharacterOffsetEnd>1067</CharacterOffsetEnd>
            <POS>NN</POS>
          </token>
          <token id="22">
            <word>and</word>
            <lemma>and</lemma>
            <CharacterOffsetBegin>1068</CharacterOffsetBegin>
            <CharacterOffsetEnd>1071</CharacterOffsetEnd>
            <POS>CC</POS>
          </token>
          <token id="23">
            <word>having</word>
            <lemma>have</lemma>
            <CharacterOffsetBegin>1072</CharacterOffsetBegin>
            <CharacterOffsetEnd>1078</CharacterOffsetEnd>
            <POS>VBG</POS>
          </token>
          <token id="24">
            <word>an</word>
            <lemma>a</lemma>
            <CharacterOffsetBegin>1079</CharacterOffsetBegin>
            <CharacterOffsetEnd>1081</CharacterOffsetEnd>
            <POS>DT</POS>
          </token>
          <token id="25">
            <word>article</word>
            <lemma>article</lemma>
            <CharacterOffsetBegin>1082</CharacterOffsetBegin>
            <CharacterOffsetEnd>1089</CharacterOffsetEnd>
            <POS>NN</POS>
          </token>
          <token id="26">
            <word>with</word>
            <lemma>with</lemma>
            <CharacterOffsetBegin>1090</CharacterOffsetBegin>
            <CharacterOffsetEnd>1094</CharacterOffsetEnd>
            <POS>IN</POS>
          </token>
          <token id="27">
            <word>a</word>
            <lemma>a</lemma>
            <CharacterOffsetBegin>1095</CharacterOffsetBegin>
            <CharacterOffsetEnd>1096</CharacterOffsetEnd>
            <POS>DT</POS>
          </token>
          <token id="28">
            <word>blade</word>
            <lemma>blade</lemma>
            <CharacterOffsetBegin>1097</CharacterOffsetBegin>
            <CharacterOffsetEnd>1102</CharacterOffsetEnd>
            <POS>NN</POS>
          </token>
          <token id="29">
            <word>.</word>
            <lemma>.</lemma>
            <CharacterOffsetBegin>1102</CharacterOffsetBegin>
            <CharacterOffsetEnd>1103</CharacterOffsetEnd>
            <POS>.</POS>
          </token>
        </tokens>
      </sentence>
      <sentence id="8">
        <tokens>
          <token id="1">
            <word>He</word>
            <lemma>he</lemma>
            <CharacterOffsetBegin>1104</CharacterOffsetBegin>
            <CharacterOffsetEnd>1106</CharacterOffsetEnd>
            <POS>PRP</POS>
          </token>
          <token id="2">
            <word>was</word>
            <lemma>be</lemma>
            <CharacterOffsetBegin>1107</CharacterOffsetBegin>
            <CharacterOffsetEnd>1110</CharacterOffsetEnd>
            <POS>VBD</POS>
          </token>
          <token id="3">
            <word>remanded</word>
            <lemma>remand</lemma>
            <CharacterOffsetBegin>1111</CharacterOffsetBegin>
            <CharacterOffsetEnd>1119</CharacterOffsetEnd>
            <POS>VBN</POS>
          </token>
          <token id="4">
            <word>in</word>
            <lemma>in</lemma>
            <CharacterOffsetBegin>1120</CharacterOffsetBegin>
            <CharacterOffsetEnd>1122</CharacterOffsetEnd>
            <POS>IN</POS>
          </token>
          <token id="5">
            <word>custody</word>
            <lemma>custody</lemma>
            <CharacterOffsetBegin>1123</CharacterOffsetBegin>
            <CharacterOffsetEnd>1130</CharacterOffsetEnd>
            <POS>NN</POS>
          </token>
          <token id="6">
            <word>and</word>
            <lemma>and</lemma>
            <CharacterOffsetBegin>1131</CharacterOffsetBegin>
            <CharacterOffsetEnd>1134</CharacterOffsetEnd>
            <POS>CC</POS>
          </token>
          <token id="7">
            <word>is</word>
            <lemma>be</lemma>
            <CharacterOffsetBegin>1135</CharacterOffsetBegin>
            <CharacterOffsetEnd>1137</CharacterOffsetEnd>
            <POS>VBZ</POS>
          </token>
          <token id="8">
            <word>due</word>
            <lemma>due</lemma>
            <CharacterOffsetBegin>1138</CharacterOffsetBegin>
            <CharacterOffsetEnd>1141</CharacterOffsetEnd>
            <POS>JJ</POS>
          </token>
          <token id="9">
            <word>to</word>
            <lemma>to</lemma>
            <CharacterOffsetBegin>1142</CharacterOffsetBegin>
            <CharacterOffsetEnd>1144</CharacterOffsetEnd>
            <POS>TO</POS>
          </token>
          <token id="10">
            <word>be</word>
            <lemma>be</lemma>
            <CharacterOffsetBegin>1145</CharacterOffsetBegin>
            <CharacterOffsetEnd>1147</CharacterOffsetEnd>
            <POS>VB</POS>
          </token>
          <token id="11">
            <word>sentenced</word>
            <lemma>sentence</lemma>
            <CharacterOffsetBegin>1148</CharacterOffsetBegin>
            <CharacterOffsetEnd>1157</CharacterOffsetEnd>
            <POS>VBN</POS>
          </token>
          <token id="12">
            <word>in</word>
            <lemma>in</lemma>
            <CharacterOffsetBegin>1158</CharacterOffsetBegin>
            <CharacterOffsetEnd>1160</CharacterOffsetEnd>
            <POS>IN</POS>
          </token>
          <token id="13">
            <word>September</word>
            <lemma>September</lemma>
            <CharacterOffsetBegin>1161</CharacterOffsetBegin>
            <CharacterOffsetEnd>1170</CharacterOffsetEnd>
            <POS>NNP</POS>
          </token>
          <token id="14">
            <word>.</word>
            <lemma>.</lemma>
            <CharacterOffsetBegin>1170</CharacterOffsetBegin>
            <CharacterOffsetEnd>1171</CharacterOffsetEnd>
            <POS>.</POS>
          </token>
        </tokens>
      </sentence>
    </sentences>
  </document>
</root>
